{
  "locations": [
    {
      "id": 1,
      "latitude": 30.68119474573654,
      "longitude": 76.72820085375321,
      "timestamp": "2025-08-12T13:32:47.073390",
      "modelUrl": "https://github.com/pratyush-talentelgia/street-view-host/raw/refs/heads/main/direction_arrow.glb",
      "scale": {
        "x": 8,
        "y": 8,
        "z": 8
      },
      "position": {
        "x": 0,
        "y": 0,
        "z": 0
      },
      "rotation": {
        "x": 0,
        "y": 0,
        "z": 0,
        "w": 2.5
      },
      "anchorTransform": [
        [
          0.7286345958709717,
          0,
          0.6849026083946228,
          0.2806659936904907
        ],
        [
          0,
          0.9999999403953552,
          0,
          -0.190691739320755
        ],
        [
          -0.684902548789978,
          0,
          0.7286345958709717,
          0.05356059968471527
        ],
        [
          0,
          0,
          0,
          1
        ]
      ]
    }
  ]
}